javascriptasync/__init__.py
javascriptasync/__main__.py
javascriptasync/asynciotasks.py
javascriptasync/commands.py
javascriptasync/configjs.py
javascriptasync/connection.py
javascriptasync/contextjs.py
javascriptasync/emitters.py
javascriptasync/errorsjs.py
javascriptasync/events.py
javascriptasync/executor.py
javascriptasync/json_patch.py
javascriptasync/logging.py
javascriptasync/proxy.py
javascriptasync/pyi.py
javascriptasync/threadtasks.py
javascriptasync/util.py
javascriptasync/core/__init__.py
javascriptasync/core/abc.py
javascriptasync/core/configbase.py
javascriptasync/core/jslogging.py
javascriptasync/core/pumlprofiler.py
javascriptasync/js/PyObject.js
javascriptasync/js/bridge.js
javascriptasync/js/deps.js
javascriptasync/js/errors.js
javascriptasync/js/pyi.js
javascriptasync-0.2.2.8.dist-info/LICENSE
javascriptasync-0.2.2.8.dist-info/METADATA
javascriptasync-0.2.2.8.dist-info/WHEEL
javascriptasync-0.2.2.8.dist-info/top_level.txt
javascriptasync-0.2.2.8.dist-info/RECORD
