Metadata-Version: 2.1
Name: javascriptasync
Version: 0.2.2.8
Summary: fork of JSPyBridge overhauled to allow for asyncio compatibility and more control.
Author-email: Crosswave Omega <xtream2pro@gmail.com>
License: The MIT License (MIT)
Project-URL: Homepage, https://github.com/CrosswaveOmega/JSPyBridge_Async
Keywords: node,javascript,bridge,development,fork
License-File: LICENSE
Provides-Extra: docs
Requires-Dist: sphinx==7.2.6; extra == "docs"
Provides-Extra: test
Requires-Dist: bandit[toml]==1.7.4; extra == "test"
Requires-Dist: black==23.1.0; extra == "test"
Requires-Dist: check-manifest==0.48; extra == "test"
Requires-Dist: flake8-bugbear==23.3.12; extra == "test"
Requires-Dist: flake8-docstrings; extra == "test"
Requires-Dist: flake8-formatter-junit-xml; extra == "test"
Requires-Dist: flake8; extra == "test"
Requires-Dist: flake8-pyproject; extra == "test"
Requires-Dist: pre-commit==2.17.0; extra == "test"
Requires-Dist: pylint==2.17.0; extra == "test"
Requires-Dist: pylint-junit; extra == "test"
Requires-Dist: pytest-cov==3.0.0; extra == "test"
Requires-Dist: pytest-mock<3.10.1; extra == "test"
Requires-Dist: pytest-runner; extra == "test"
Requires-Dist: pytest==7.2.2; extra == "test"
Requires-Dist: pytest-github-actions-annotate-failures; extra == "test"
Requires-Dist: shellcheck-py==0.9.0.2; extra == "test"
